CHANGELOG.md
LICENSE
README.md
alarmer/__init__.py
alarmer/encoder.py
alarmer/log.py
alarmer/provider/__init__.py
alarmer/provider/apprise.py
alarmer/provider/feishu.py
alarmer/provider/wecom.py
alarmer/throttling.py
alarmer-0.1.4.dist-info/LICENSE
alarmer-0.1.4.dist-info/WHEEL
alarmer-0.1.4.dist-info/METADATA
alarmer-0.1.4.dist-info/RECORD
