Metadata-Version: 2.1
Name: alarmer
Version: 0.1.4
Summary: A tool focus on error reporting for your application
Home-page: https://github.com/long2ice/alarmer
License: Apache-2.0
Keywords: sentry,error,alert,alarm
Author: long2ice
Author-email: long2ice@gmail.com
Requires-Python: >=3.7,<4.0
Classifier: License :: OSI Approved :: Apache Software License
Classifier: Programming Language :: Python :: 3
Classifier: Programming Language :: Python :: 3.7
Classifier: Programming Language :: Python :: 3.8
Classifier: Programming Language :: Python :: 3.9
Requires-Dist: apprise
Requires-Dist: better-exceptions
Project-URL: Documentation, https://github.com/long2ice/alarmer
Project-URL: Repository, https://github.com/long2ice/alarmer.git
